jsp_vis/__init__.py
jsp_vis/console.py
jsp_vis/cv2_window.py
jsp_vis/rgb_array.py
jsp_vis-1.1.0.dist-info/LICENSE
jsp_vis-1.1.0.dist-info/METADATA
jsp_vis-1.1.0.dist-info/WHEEL
jsp_vis-1.1.0.dist-info/top_level.txt
jsp_vis-1.1.0.dist-info/RECORD
