Metadata-Version: 2.1
Name: jsp-vis
Version: 1.1.0
Summary: A visualization tool for job shop scheduling problems.
Author: Alexander Nasuta
Author-email: Alexander Nasuta <alexander.nasuta@wzl-iqs.rwth-aachen.de>
License: MIT License
Project-URL: Homepage, https://github.com/Alexander-Nasuta/jsp-vis
Platform: unix
Platform: linux
Platform: osx
Platform: cygwin
Platform: win32
Classifier: License :: OSI Approved :: MIT License
Classifier: Programming Language :: Python
Classifier: Programming Language :: Python :: 3
Requires-Python: >=3.9
License-File: LICENSE
Requires-Dist: opencv-python
Requires-Dist: plotly
Requires-Dist: matplotlib <3.9
Requires-Dist: numpy
Requires-Dist: pandas
Requires-Dist: kaleido
Provides-Extra: dev
Requires-Dist: pip-tools ; extra == 'dev'
Requires-Dist: pytest ; extra == 'dev'
Requires-Dist: pytest-cov ; extra == 'dev'
Requires-Dist: tox ; extra == 'dev'
Requires-Dist: twine ; extra == 'dev'
